apk_info-1.0.9.dist-info/METADATA
apk_info-1.0.9.dist-info/WHEEL
apk_info/__init__.py
apk_info/__init__.pyi
apk_info/apk_info.pypy311-pp73-x86_64-linux-gnu.so
apk_info/py.typed
apk_info-1.0.9.dist-info/RECORD
