Metadata-Version: 2.4
Name: apk-info
Version: 1.0.9
Classifier: Programming Language :: Rust
Classifier: Programming Language :: Python :: Implementation :: CPython
Classifier: Programming Language :: Python :: Implementation :: PyPy
Requires-Dist: pytest ; extra == 'tests'
Provides-Extra: tests
Summary: APK full-featured parser
Keywords: android,apk,arsc,axml,malware
Home-Page: https://github.com/delvinru/apk-info
License: Apache-2.0
Requires-Python: >=3.10
